geckopy/__init__.py
geckopy/data.py
geckopy/gecko.py
geckopy/data_files/.gitkeep
geckopy/data_files/ecYeastGEM_multi-pool.xml
geckopy/data_files/ecYeastGEM_single-pool.xml
geckopy/data_files/proteins.txt
geckopy/data_files/sanchez-mmol_gdw.csv
geckopy-2.0.2.dist-info/AUTHORS.rst
geckopy-2.0.2.dist-info/LICENSE
geckopy-2.0.2.dist-info/METADATA
geckopy-2.0.2.dist-info/WHEEL
geckopy-2.0.2.dist-info/top_level.txt
geckopy-2.0.2.dist-info/RECORD
