Metadata-Version: 2.1
Name: geckopy
Version: 2.0.2
Summary: Methods for using the GECKO model with cobrapy
Home-page: https://github.com/SysBioChalmers/GECKO/tree/master/geckopy
Author: Benjamin Sanchez
Author-email: bensan@chalmers.se
License: MIT License
Keywords: geckopy
Platform: UNKNOWN
Classifier: Development Status :: 2 - Pre-Alpha
Classifier: Intended Audience :: Developers
Classifier: License :: OSI Approved :: MIT License
Classifier: Natural Language :: English
Classifier: Programming Language :: Python :: 2
Classifier: Programming Language :: Python :: 2.7
Classifier: Programming Language :: Python :: 3
Classifier: Programming Language :: Python :: 3.4
Classifier: Programming Language :: Python :: 3.5
Classifier: Programming Language :: Python :: 3.6
Requires-Dist: cobra (>=0.8.2)
